Metadata-Version: 2.1
Name: odoo-addon-base_rest
Version: 18.0.1.1.1.2
Requires-Python: >=3.10
Requires-Dist: apispec
Requires-Dist: cerberus
Requires-Dist: odoo-addon-component==18.0.*
Requires-Dist: odoo==18.0.*
Requires-Dist: parse-accept-language
Requires-Dist: pyquerystring
Summary: Develop your own high level REST APIs for Odoo thanks to this addon.
Home-page: https://github.com/OCA/rest-framework
License: LGPL-3
Author: ACSONE SA/NV, Odoo Community Association (OCA)
Author-email: support@odoo-community.org
Classifier: Programming Language :: Python
Classifier: Framework :: Odoo
Classifier: Framework :: Odoo :: 18.0
Classifier: License :: OSI Approved :: GNU Lesser General Public License v3 (LGPLv3)
Classifier: Development Status :: 4 - Beta
